arvancloud/video/__init__.py
arvancloud/video/client.py
arvancloud/video/helpers/__init__.py
arvancloud/video/helpers/error.py
arvancloud/video/interfaces/__init__.py
arvancloud/video/interfaces/ad.py
arvancloud/video/interfaces/audio.py
arvancloud/video/interfaces/campaign.py
arvancloud/video/interfaces/campaign_ad.py
arvancloud/video/interfaces/channel.py
arvancloud/video/interfaces/profile.py
arvancloud/video/interfaces/query_params.py
arvancloud/video/interfaces/stream.py
arvancloud/video/interfaces/vads_channel.py
arvancloud/video/interfaces/video.py
arvancloud/video/interfaces/watermark.py
arvancloud/video/video_app/__init__.py
arvancloud/video/video_app/ads.py
arvancloud/video/video_app/audios.py
arvancloud/video/video_app/campaigns.py
arvancloud/video/video_app/channels.py
arvancloud/video/video_app/domains.py
arvancloud/video/video_app/files.py
arvancloud/video/video_app/live.py
arvancloud/video/video_app/profiles.py
arvancloud/video/video_app/videos.py
arvancloud/video/video_app/watermarks.py
arvancloud_video-0.1.0.dist-info/METADATA
arvancloud_video-0.1.0.dist-info/WHEEL
arvancloud_video-0.1.0.dist-info/RECORD
