Metadata-Version: 2.1
Name: arvancloud-video
Version: 0.1.0
Summary: The ArvanCloud Video Platform SDK for Python
Author: Video Team.
Author-email: video@arvancloud.ir
Requires-Python: >=3.9,<4.0
Classifier: Programming Language :: Python :: 3
Classifier: Programming Language :: Python :: 3.9
Classifier: Programming Language :: Python :: 3.10
Classifier: Programming Language :: Python :: 3.11
Requires-Dist: pytest (>=3.0.5,<4.0.0)
Requires-Dist: python-dotenv (>=1.0.0,<2.0.0)
Requires-Dist: python-magic (>=0.4.27,<0.5.0)
Requires-Dist: requests (>=2.25.0,<3.0.0)
Requires-Dist: termcolor (>=2.3.0,<3.0.0)
Requires-Dist: urllib3 (>=2.0.3,<3.0.0)
